MANIFEST.in
README.txt
setup.cfg
setup.py
docs/LICENSE.GPL
docs/LICENSE.txt
docs/screenshot.png
plonetheme/__init__.py
plonetheme.twinapex.egg-info/PKG-INFO
plonetheme.twinapex.egg-info/SOURCES.txt
plonetheme.twinapex.egg-info/dependency_links.txt
plonetheme.twinapex.egg-info/entry_points.txt
plonetheme.twinapex.egg-info/namespace_packages.txt
plonetheme.twinapex.egg-info/not-zip-safe
plonetheme.twinapex.egg-info/requires.txt
plonetheme.twinapex.egg-info/top_level.txt
plonetheme/twinapex/__init__.py
plonetheme/twinapex/configure.zcml
plonetheme/twinapex/extender.py
plonetheme/twinapex/interfaces.py
plonetheme/twinapex/profiles.zcml
plonetheme/twinapex/setuphandlers.py
plonetheme/twinapex/skins.zcml
plonetheme/twinapex/tests.py
plonetheme/twinapex/browser/__init__.py
plonetheme/twinapex/browser/configure.zcml
plonetheme/twinapex/browser/interfaces.py
plonetheme/twinapex/browser/utilities.py
plonetheme/twinapex/browser/viewlet.pt
plonetheme/twinapex/browser/images/README.txt
plonetheme/twinapex/browser/images/Search.gif
plonetheme/twinapex/browser/images/accessibility-trans.png
plonetheme/twinapex/browser/images/contact-trans.png
plonetheme/twinapex/browser/images/header-narrowed.jpg
plonetheme/twinapex/browser/images/header.jpg
plonetheme/twinapex/browser/images/li.png
plonetheme/twinapex/browser/images/li_blue.png
plonetheme/twinapex/browser/images/li_grey.png
plonetheme/twinapex/browser/images/menubar.png
plonetheme/twinapex/browser/images/portlet_header.png
plonetheme/twinapex/browser/images/print-trans.png
plonetheme/twinapex/browser/images/searchbg.gif
plonetheme/twinapex/browser/images/shadow-left.gif
plonetheme/twinapex/browser/images/shadow-left.png
plonetheme/twinapex/browser/images/shadow-right.gif
plonetheme/twinapex/browser/images/sitemap-trans.png
plonetheme/twinapex/browser/images/stripe.png
plonetheme/twinapex/browser/portlets/__init__.py
plonetheme/twinapex/browser/portlets/configure.zcml
plonetheme/twinapex/browser/portlets/grey_static.pt
plonetheme/twinapex/browser/portlets/misc.py
plonetheme/twinapex/browser/portlets/navigation.pt
plonetheme/twinapex/browser/portlets/navigation.py
plonetheme/twinapex/browser/portlets/navigation_recurse.pt
plonetheme/twinapex/browser/portlets/news.pt
plonetheme/twinapex/browser/portlets/section_navigation.pt
