Metadata-Version: 1.0
Name: plonetheme.twinapex
Version: 1.0.4
Summary: Twinapex Theme is a theming product for Plone to give your site a professional corporate look
Home-page: http://www.twinapex.com
Author: Mikko Ohtamaa
Author-email: research@twinapex.com
License: GPL
Keywords: twinapex web zope plone theme skin corporate
Platform: UNKNOWN
Classifier: Framework :: Plone
Classifier: Framework :: Zope2
Classifier: Framework :: Zope3
Classifier: Programming Language :: Python
Classifier: Topic :: Software Development :: Libraries :: Python Modules
